array2image-0.1.0.dist-info/METADATA
array2image-0.1.0.dist-info/WHEEL
array2image-0.1.0.dist-info/licenses/LICENSE
array2image/__init__.py
array2image/core.py
array2image-0.1.0.dist-info/RECORD
