Metadata-Version: 2.1
Name: array2image
Version: 0.1.0
Summary: Converts a Numpy array to a PIL image.
Author-Email: Matthieu Thiboust <14574229+mthiboust@users.noreply.github.com>
License: Apache 2.0
Requires-Python: >=3.10
Requires-Dist: numpy>=1.26.2
Requires-Dist: pillow>=8.4.0
